<?xml version="1.0" encoding="utf-8"?>
<executable>
    <category>Cardiac MRI Toolkit</category> 
    <title>LA Segmentation Using Graph Cuts</title>
    <description>This module implements an algorithm to automatically segment out the Left Atrium from an LGE-MRI image volume.</description>
    <version>0.1.0</version>
    <documentation-url></documentation-url>
    <license>Slicer</license>
    <contributor>Gopal Veni, Salma Bengali, Greg Gardner, Alan Morris, Josh Cates, Rob MacLeod, Ross Whitaker</contributor>
    <acknowledgements><![CDATA[This work was supported by ...]]></acknowledgements>
    <parameters>
        <label>IO</label>
        <description>Input/output parameters</description>
        <image>
            <name>inputImage</name>
            <label>Input Image</label>
            <index>0</index>
            <channel>input</channel>
            <description><![CDATA[Cardiac LGE-MRI input image volume]]></description>
        </image>
        <integer>
            <name>deltaS</name>
            <label>Smoothness Parameter</label>
            <index>1</index>
            <channel>input</channel>
            <constraints>
                <minimum> 4 </minimum>
                <maximum> 10 </maximum>
                <step> 1 </step>
            </constraints>
            <description><![CDATA[Smoothness constraint for a surface (range 4-10)]]></description>
        </integer>
        <integer>
            <name>MdlOption</name>
            <label>Model selection Parameter</label>
            <index>2</index>
            <channel>input</channel>
            <constraints>
                <minimum> 1 </minimum>
                <maximum> 5 </maximum>
                <step> 1 </step>
            </constraints>
            <description><![CDATA[Selection of model number]]></description>
        </integer>
        <image type="label">
            <name>outputImage</name>
            <label>Output Image</label>
            <index>3</index>
            <channel>output</channel>
            <description><![CDATA[The segmented output image volume]]></description>
        </image>
        <directory>
            <name>inputDataDirectory</name>
            <label>Input Data Directory</label>
            <index>4</index>
            <channel>input</channel>
            <description><![CDATA[The directory from which to import a specific model's data]]></description>
        </directory> 
	<geometry fileExtensions=".vtk">
            <name>epiMesh</name>
            <label>Epi Mesh</label>
            <index>5</index>
            <channel>output</channel>
            <description><![CDATA[The output epi mesh]]></description>
	</geometry>
	<geometry fileExtensions=".vtk">
            <name>endoMesh</name>
            <label>Endo Mesh</label>
            <index>6</index>
            <channel>output</channel>
            <description><![CDATA[The output endo mesh]]></description>
	</geometry>
        <float>
            <name>row</name>
            <label>Row</label>
            <index>7</index>
            <channel>input</channel>
            <description><![CDATA[Manually select the center of mass of the LA and enter the row]]></description>
        </float>
        <float>
            <name>column</name>
            <label>Column</label>
            <index>8</index>
            <channel>input</channel>
            <description><![CDATA[Manually select the center of mass of the LA and enter the column]]></description>
        </float>
        <float>
            <name>slice</name>
            <label>Slice</label>
            <index>9</index>
            <channel>input</channel>
            <description><![CDATA[Manually select the center of mass of the LA and enter the slice]]></description>
        </float>
    </parameters>
</executable>
